margindash/__init__.py
margindash/client.py
margindash/queue.py
margindash/retry.py
margindash/serializer.py
margindash/types.py
margindash-0.1.1.dist-info/METADATA
margindash-0.1.1.dist-info/WHEEL
margindash-0.1.1.dist-info/licenses/LICENSE
margindash-0.1.1.dist-info/RECORD
